README.rst
setup.py
AskheavenTools/__init__.py
AskheavenTools/function.py
AskheavenTools/strlib.py
Askheaventext.egg-info/PKG-INFO
Askheaventext.egg-info/SOURCES.txt
Askheaventext.egg-info/dependency_links.txt
Askheaventext.egg-info/not-zip-safe
Askheaventext.egg-info/top_level.txt