Metadata-Version: 1.1
Name: Askheaventext
Version: 2.0
Summary: 测试
Home-page: https://github.com
Author: Askheaven
Author-email: 278842015@qq.com
License: BSD
Platform: UNKNOWN
Classifier: Development Status :: 3 - Alpha
Classifier: Environment :: Web Environment
Classifier: Intended Audience :: Developers
Classifier: License :: OSI Approved :: BSD License
Classifier: Operating System :: OS Independent
Classifier: Programming Language :: Python
Classifier: Framework :: Django
